Workbook

Sheet ReadMe
A1: Synthetic DCF test workbook
A3: This file is intentionally low-quality and uses made-up assumptions for software/testing purposes.
A5: Formulas are included; values recalculate in Excel/Google Sheets.

Sheet Assumptions
A1: Assumption | B1: Value | D1: Year | E1: Revenue Growth
A2: Base Revenue ($mm) | B2: 1000 | D2: 2026E | E2: 0.12
A3: EBIT Margin | B3: 0.22 | D3: 2027E | E3: 0.1
A4: Tax Rate | B4: 0.25 | D4: 2028E | E4: 0.08
A5: D&A % Revenue | B5: 0.03 | D5: 2029E | E5: 0.06
A6: Capex % Revenue | B6: 0.04 | D6: 2030E | E6: 0.04
A7: NWC % Revenue | B7: 0.1
A8: WACC | B8: 0.1
A9: Terminal Growth | B9: 0.025
A10: Net Debt ($mm) | B10: 350
A11: Shares Outstanding (mm) | B11: 120

Sheet Projection
A1: Projection ($mm)
B3: =Assumptions!D2 | C3: =Assumptions!D3 | D3: =Assumptions!D4 | E3: =Assumptions!D5 | F3: =Assumptions!D6
B4: 1 | C4: 2 | D4: 3 | E4: 4 | F4: 5
A5: Revenue | B5: =Assumptions!$B$2*(1+B6) | C5: =B5*(1+C6) | D5: =C5*(1+D6) | E5: =D5*(1+E6) | F5: =E5*(1+F6)
A6: Growth | B6: =Assumptions!E2 | C6: =Assumptions!E3 | D6: =Assumptions!E4 | E6: =Assumptions!E5 | F6: =Assumptions!E6
A7: EBIT | B7: =B5*Assumptions!$B$3 | C7: =C5*Assumptions!$B$3 | D7: =D5*Assumptions!$B$3 | E7: =E5*Assumptions!$B$3 | F7: =F5*Assumptions!$B$3
A8: Taxes | B8: =-B7*Assumptions!$B$4 | C8: =-C7*Assumptions!$B$4 | D8: =-D7*Assumptions!$B$4 | E8: =-E7*Assumptions!$B$4 | F8: =-F7*Assumptions!$B$4
A9: NOPAT | B9: =B7+B8 | C9: =C7+C8 | D9: =D7+D8 | E9: =E7+E8 | F9: =F7+F8
A10: D&A | B10: =B5*Assumptions!$B$5 | C10: =C5*Assumptions!$B$5 | D10: =D5*Assumptions!$B$5 | E10: =E5*Assumptions!$B$5 | F10: =F5*Assumptions!$B$5
A11: Capex | B11: =-B5*Assumptions!$B$6 | C11: =-C5*Assumptions!$B$6 | D11: =-D5*Assumptions!$B$6 | E11: =-E5*Assumptions!$B$6 | F11: =-F5*Assumptions!$B$6
A12: NWC Balance | B12: =B5*Assumptions!$B$7 | C12: =C5*Assumptions!$B$7 | D12: =D5*Assumptions!$B$7 | E12: =E5*Assumptions!$B$7 | F12: =F5*Assumptions!$B$7
A13: Change in NWC | B13: =-(B12-Assumptions!$B$2*Assumptions!$B$7) | C13: =-(C12-B12) | D13: =-(D12-C12) | E13: =-(E12-D12) | F13: =-(F12-E12)
A14: UFCF | B14: =B9+B10+B11+B13 | C14: =C9+C10+C11+C13 | D14: =D9+D10+D11+D13 | E14: =E9+E10+E11+E13 | F14: =F9+F10+F11+F13

Sheet DCF
A1: DCF Valuation
B3: =Projection!B3 | C3: =Projection!C3 | D3: =Projection!D3 | E3: =Projection!E3 | F3: =Projection!F3
A5: Period | B5: =Projection!B4 | C5: =Projection!C4 | D5: =Projection!D4 | E5: =Projection!E4 | F5: =Projection!F4
A6: UFCF | B6: =Projection!B14 | C6: =Projection!C14 | D6: =Projection!D14 | E6: =Projection!E14 | F6: =Projection!F14
A7: Discount Factor | B7: =1/(1+Assumptions!$B$8)^B5 | C7: =1/(1+Assumptions!$B$8)^C5 | D7: =1/(1+Assumptions!$B$8)^D5 | E7: =1/(1+Assumptions!$B$8)^E5 | F7: =1/(1+Assumptions!$B$8)^F5
A8: PV of UFCF | B8: =B6*B7 | C8: =C6*C7 | D8: =D6*D7 | E8: =E6*E7 | F8: =F6*F7
A10: Terminal FCF | B10: =F6*(1+Assumptions!$B$9)
A11: Terminal Value | B11: =B10/(Assumptions!$B$8-Assumptions!$B$9)
A12: PV Factor @ Year 5 | B12: =F7
A13: PV of Terminal Value | B13: =B11*B12
A15: Enterprise Value | B15: =SUM(B8:F8)+B13
A16: Less: Net Debt | B16: =-Assumptions!$B$10
A17: Equity Value | B17: =B15+B16
A18: Shares Outstanding (mm) | B18: =Assumptions!$B$11
A19: Implied Price / Share | B19: =B17/B18
A21: Check (WACC > g) | B21: =IF(Assumptions!$B$8>Assumptions!$B$9,"OK","ERROR")

Sheet Sensitivity
A1: Price / Share Sensitivity
B2: Terminal Growth \\ WACC | C2: 0.08 | D2: 0.09 | E2: 0.1 | F2: 0.11 | G2: 0.12
B3: 0.01 | C3: =IF(C$2<=$B3,NA(),((SUMPRODUCT(DCF!$B$6:$F$6,1/(1+C$2)^(DCF!$B$5:$F$5))+((DCF!$F$6*(1+$B3))/(C$2-$B3))*(1/(1+C$2)^DCF!$F$5)-Assumptions!$B$10)/Assumptions!$B$11)) | D3: =IF(D$2<=$B3,NA(),((SUMPRODUCT(DCF!$B$6:$F$6,1/(1+D$2)^(DCF!$B$5:$F$5))+((DCF!$F$6*(1+$B3))/(D$2-$B3))*(1/(1+D$2)^DCF!$F$5)-Assumptions!$B$10)/Assumptions!$B$11)) | E3: =IF(E$2<=$B3,NA(),((SUMPRODUCT(DCF!$B$6:$F$6,1/(1+E$2)^(DCF!$B$5:$F$5))+((DCF!$F$6*(1+$B3))/(E$2-$B3))*(1/(1+E$2)^DCF!$F$5)-Assumptions!$B$10)/Assumptions!$B$11)) | F3: =IF(F$2<=$B3,NA(),((SUMPRODUCT(DCF!$B$6:$F$6,1/(1+F$2)^(DCF!$B$5:$F$5))+((DCF!$F$6*(1+$B3))/(F$2-$B3))*(1/(1+F$2)^DCF!$F$5)-Assumptions!$B$10)/Assumptions!$B$11)) | G3: =IF(G$2<=$B3,NA(),((SUMPRODUCT(DCF!$B$6:$F$6,1/(1+G$2)^(DCF!$B$5:$F$5))+((DCF!$F$6*(1+$B3))/(G$2-$B3))*(1/(1+G$2)^DCF!$F$5)-Assumptions!$B$10)/Assumptions!$B$11))
B4: 0.02 | C4: =IF(C$2<=$B4,NA(),((SUMPRODUCT(DCF!$B$6:$F$6,1/(1+C$2)^(DCF!$B$5:$F$5))+((DCF!$F$6*(1+$B4))/(C$2-$B4))*(1/(1+C$2)^DCF!$F$5)-Assumptions!$B$10)/Assumptions!$B$11)) | D4: =IF(D$2<=$B4,NA(),((SUMPRODUCT(DCF!$B$6:$F$6,1/(1+D$2)^(DCF!$B$5:$F$5))+((DCF!$F$6*(1+$B4))/(D$2-$B4))*(1/(1+D$2)^DCF!$F$5)-Assumptions!$B$10)/Assumptions!$B$11)) | E4: =IF(E$2<=$B4,NA(),((SUMPRODUCT(DCF!$B$6:$F$6,1/(1+E$2)^(DCF!$B$5:$F$5))+((DCF!$F$6*(1+$B4))/(E$2-$B4))*(1/(1+E$2)^DCF!$F$5)-Assumptions!$B$10)/Assumptions!$B$11)) | F4: =IF(F$2<=$B4,NA(),((SUMPRODUCT(DCF!$B$6:$F$6,1/(1+F$2)^(DCF!$B$5:$F$5))+((DCF!$F$6*(1+$B4))/(F$2-$B4))*(1/(1+F$2)^DCF!$F$5)-Assumptions!$B$10)/Assumptions!$B$11)) | G4: =IF(G$2<=$B4,NA(),((SUMPRODUCT(DCF!$B$6:$F$6,1/(1+G$2)^(DCF!$B$5:$F$5))+((DCF!$F$6*(1+$B4))/(G$2-$B4))*(1/(1+G$2)^DCF!$F$5)-Assumptions!$B$10)/Assumptions!$B$11))
B5: 0.025 | C5: =IF(C$2<=$B5,NA(),((SUMPRODUCT(DCF!$B$6:$F$6,1/(1+C$2)^(DCF!$B$5:$F$5))+((DCF!$F$6*(1+$B5))/(C$2-$B5))*(1/(1+C$2)^DCF!$F$5)-Assumptions!$B$10)/Assumptions!$B$11)) | D5: =IF(D$2<=$B5,NA(),((SUMPRODUCT(DCF!$B$6:$F$6,1/(1+D$2)^(DCF!$B$5:$F$5))+((DCF!$F$6*(1+$B5))/(D$2-$B5))*(1/(1+D$2)^DCF!$F$5)-Assumptions!$B$10)/Assumptions!$B$11)) | E5: =IF(E$2<=$B5,NA(),((SUMPRODUCT(DCF!$B$6:$F$6,1/(1+E$2)^(DCF!$B$5:$F$5))+((DCF!$F$6*(1+$B5))/(E$2-$B5))*(1/(1+E$2)^DCF!$F$5)-Assumptions!$B$10)/Assumptions!$B$11)) | F5: =IF(F$2<=$B5,NA(),((SUMPRODUCT(DCF!$B$6:$F$6,1/(1+F$2)^(DCF!$B$5:$F$5))+((DCF!$F$6*(1+$B5))/(F$2-$B5))*(1/(1+F$2)^DCF!$F$5)-Assumptions!$B$10)/Assumptions!$B$11)) | G5: =IF(G$2<=$B5,NA(),((SUMPRODUCT(DCF!$B$6:$F$6,1/(1+G$2)^(DCF!$B$5:$F$5))+((DCF!$F$6*(1+$B5))/(G$2-$B5))*(1/(1+G$2)^DCF!$F$5)-Assumptions!$B$10)/Assumptions!$B$11))
B6: 0.03 | C6: =IF(C$2<=$B6,NA(),((SUMPRODUCT(DCF!$B$6:$F$6,1/(1+C$2)^(DCF!$B$5:$F$5))+((DCF!$F$6*(1+$B6))/(C$2-$B6))*(1/(1+C$2)^DCF!$F$5)-Assumptions!$B$10)/Assumptions!$B$11)) | D6: =IF(D$2<=$B6,NA(),((SUMPRODUCT(DCF!$B$6:$F$6,1/(1+D$2)^(DCF!$B$5:$F$5))+((DCF!$F$6*(1+$B6))/(D$2-$B6))*(1/(1+D$2)^DCF!$F$5)-Assumptions!$B$10)/Assumptions!$B$11)) | E6: =IF(E$2<=$B6,NA(),((SUMPRODUCT(DCF!$B$6:$F$6,1/(1+E$2)^(DCF!$B$5:$F$5))+((DCF!$F$6*(1+$B6))/(E$2-$B6))*(1/(1+E$2)^DCF!$F$5)-Assumptions!$B$10)/Assumptions!$B$11)) | F6: =IF(F$2<=$B6,NA(),((SUMPRODUCT(DCF!$B$6:$F$6,1/(1+F$2)^(DCF!$B$5:$F$5))+((DCF!$F$6*(1+$B6))/(F$2-$B6))*(1/(1+F$2)^DCF!$F$5)-Assumptions!$B$10)/Assumptions!$B$11)) | G6: =IF(G$2<=$B6,NA(),((SUMPRODUCT(DCF!$B$6:$F$6,1/(1+G$2)^(DCF!$B$5:$F$5))+((DCF!$F$6*(1+$B6))/(G$2-$B6))*(1/(1+G$2)^DCF!$F$5)-Assumptions!$B$10)/Assumptions!$B$11))
B7: 0.04 | C7: =IF(C$2<=$B7,NA(),((SUMPRODUCT(DCF!$B$6:$F$6,1/(1+C$2)^(DCF!$B$5:$F$5))+((DCF!$F$6*(1+$B7))/(C$2-$B7))*(1/(1+C$2)^DCF!$F$5)-Assumptions!$B$10)/Assumptions!$B$11)) | D7: =IF(D$2<=$B7,NA(),((SUMPRODUCT(DCF!$B$6:$F$6,1/(1+D$2)^(DCF!$B$5:$F$5))+((DCF!$F$6*(1+$B7))/(D$2-$B7))*(1/(1+D$2)^DCF!$F$5)-Assumptions!$B$10)/Assumptions!$B$11)) | E7: =IF(E$2<=$B7,NA(),((SUMPRODUCT(DCF!$B$6:$F$6,1/(1+E$2)^(DCF!$B$5:$F$5))+((DCF!$F$6*(1+$B7))/(E$2-$B7))*(1/(1+E$2)^DCF!$F$5)-Assumptions!$B$10)/Assumptions!$B$11)) | F7: =IF(F$2<=$B7,NA(),((SUMPRODUCT(DCF!$B$6:$F$6,1/(1+F$2)^(DCF!$B$5:$F$5))+((DCF!$F$6*(1+$B7))/(F$2-$B7))*(1/(1+F$2)^DCF!$F$5)-Assumptions!$B$10)/Assumptions!$B$11)) | G7: =IF(G$2<=$B7,NA(),((SUMPRODUCT(DCF!$B$6:$F$6,1/(1+G$2)^(DCF!$B$5:$F$5))+((DCF!$F$6*(1+$B7))/(G$2-$B7))*(1/(1+G$2)^DCF!$F$5)-Assumptions!$B$10)/Assumptions!$B$11))
